montaigne/__init__.py
montaigne/__main__.py
montaigne/annotation.py
montaigne/annotation_server.py
montaigne/app.py
montaigne/audio.py
montaigne/branding.py
montaigne/cli.py
montaigne/cloud_api.py
montaigne/cloud_config.py
montaigne/cloud_storage.py
montaigne/config.py
montaigne/coqui_tts.py
montaigne/elevenlabs_tts.py
montaigne/images.py
montaigne/logging.py
montaigne/media_cli.py
montaigne/pdf.py
montaigne/ppt.py
montaigne/scripts.py
montaigne/video.py
montaigne/assets/montaigne-logo-amber.png
montaigne-1.1.1.dist-info/licenses/LICENSE
montaigne-1.1.1.dist-info/METADATA
montaigne-1.1.1.dist-info/WHEEL
montaigne-1.1.1.dist-info/entry_points.txt
montaigne-1.1.1.dist-info/top_level.txt
montaigne-1.1.1.dist-info/RECORD
