Metadata-Version: 2.4
Name: montaigne
Version: 1.1.1
Summary: Media processing toolkit for presentation localization
Author: Yann Debray
License: MIT
Project-URL: Homepage, https://github.com/yanndebray/montaigne
Project-URL: Documentation, https://github.com/yanndebray/montaigne#readme
Project-URL: Repository, https://github.com/yanndebray/montaigne
Keywords: gemini,ai,localization,pdf,audio,tts,translation
Classifier: Development Status :: 5 - Production/Stable
Classifier: Intended Audience :: Developers
Classifier: License :: OSI Approved :: MIT License
Classifier: Programming Language :: Python :: 3
Classifier: Programming Language :: Python :: 3.10
Classifier: Programming Language :: Python :: 3.11
Classifier: Programming Language :: Python :: 3.12
Classifier: Topic :: Multimedia :: Sound/Audio :: Speech
Classifier: Topic :: Scientific/Engineering :: Image Processing
Requires-Python: >=3.10
License-File: LICENSE
Requires-Dist: google-genai>=1.0.0
Requires-Dist: python-dotenv>=1.0.0
Requires-Dist: pymupdf>=1.24.0
Requires-Dist: python-pptx>=0.6.21
Requires-Dist: Pillow>=10.0.0
Requires-Dist: tqdm>=4.65.0
Requires-Dist: requests>=2.28.0
Requires-Dist: elevenlabs>=2.29.0
Provides-Extra: dev
Requires-Dist: pytest>=7.0.0; extra == "dev"
Requires-Dist: pytest-cov>=4.0.0; extra == "dev"
Requires-Dist: black==24.10.0; extra == "dev"
Requires-Dist: ruff>=0.1.0; extra == "dev"
Provides-Extra: edit
Requires-Dist: streamlit>=1.30.0; extra == "edit"
Provides-Extra: annotate
Requires-Dist: flask>=3.0.0; extra == "annotate"
Provides-Extra: coqui
Requires-Dist: TTS>=0.22.0; extra == "coqui"
Requires-Dist: torch<2.6,>=2.4.0; extra == "coqui"
Requires-Dist: torchaudio<2.6,>=2.4.0; extra == "coqui"
Requires-Dist: transformers<4.50,>=4.40.0; extra == "coqui"
Provides-Extra: cloud
Requires-Dist: fastapi>=0.100.0; extra == "cloud"
Requires-Dist: uvicorn[standard]>=0.20.0; extra == "cloud"
Requires-Dist: google-cloud-storage>=2.10.0; extra == "cloud"
Requires-Dist: python-multipart>=0.0.6; extra == "cloud"
Provides-Extra: all
Requires-Dist: montaigne[annotate,cloud,coqui,dev,edit]; extra == "all"
Dynamic: license-file
